[
  {
    "ts": "2026-05-21T19:05:41Z",
    "classified": 67,
    "builder": 20,
    "not_builder": 47,
    "unclear": 0,
    "builder_rate": 0.2985,
    "title_skipped": 28,
    "location_skipped": 3
  },
  {
    "ts": "2026-05-21T20:00:20Z",
    "classified": 84,
    "builder": 23,
    "not_builder": 61,
    "unclear": 0,
    "builder_rate": 0.2738,
    "title_skipped": 61,
    "location_skipped": 7
  },
  {
    "ts": "2026-05-21T21:04:44Z",
    "classified": 127,
    "builder": 44,
    "not_builder": 83,
    "unclear": 0,
    "builder_rate": 0.3465,
    "title_skipped": 69,
    "location_skipped": 3
  },
  {
    "ts": "2026-05-21T21:38:38Z",
    "classified": 57,
    "builder": 11,
    "not_builder": 46,
    "unclear": 0,
    "builder_rate": 0.193,
    "title_skipped": 37,
    "location_skipped": 5
  },
  {
    "ts": "2026-05-21T21:57:46Z",
    "classified": 108,
    "builder": 9,
    "not_builder": 99,
    "unclear": 0,
    "builder_rate": 0.0833,
    "title_skipped": 134,
    "location_skipped": 82
  },
  {
    "ts": "2026-05-21T22:51:35Z",
    "classified": 63,
    "builder": 16,
    "not_builder": 47,
    "unclear": 0,
    "builder_rate": 0.254,
    "title_skipped": 54,
    "location_skipped": 13
  },
  {
    "ts": "2026-05-21T23:41:40Z",
    "classified": 44,
    "builder": 15,
    "not_builder": 29,
    "unclear": 0,
    "builder_rate": 0.3409,
    "title_skipped": 28,
    "location_skipped": 0
  }
]